howmany/__init__.py
howmany/compare.py
howmany/utils.py
howmany-0.2.1.dist-info/LICENSE.txt
howmany-0.2.1.dist-info/METADATA
howmany-0.2.1.dist-info/WHEEL
howmany-0.2.1.dist-info/top_level.txt
howmany-0.2.1.dist-info/RECORD
