Metadata-Version: 2.1
Name: howmany
Version: 0.2.1
Summary: Wikidata powered comparisons
Home-page: https://github.com/andrewtavis/howmany
Author: Andrew Tavis McAllister
Author-email: andrew.t.mcallister@gmail.com
License: new BSD
Classifier: Development Status :: 5 - Production/Stable
Classifier: Intended Audience :: Developers
Classifier: Intended Audience :: Education
Classifier: Intended Audience :: Science/Research
Classifier: License :: OSI Approved :: BSD License
Classifier: Programming Language :: Python
Classifier: Programming Language :: Python :: 3
Classifier: Programming Language :: Python :: 3.8
Classifier: Programming Language :: Python :: 3.9
Classifier: Programming Language :: Python :: 3.10
Classifier: Programming Language :: Python :: 3.11
Classifier: Operating System :: OS Independent
Requires-Python: >=3.8
License-File: LICENSE.txt
Requires-Dist: pytest-cov (>=4.1.0)
Requires-Dist: tqdm (>=4.56.1)
